setup.py
zindex/__init__.py
zindex/zindex.py
zindex.egg-info/PKG-INFO
zindex.egg-info/SOURCES.txt
zindex.egg-info/dependency_links.txt
zindex.egg-info/requires.txt
zindex.egg-info/top_level.txt