Metadata-Version: 1.0
Name: zindex
Version: 0.1.0
Summary: Z-Index based sorting and querying of sparse matrices
Home-page: UNKNOWN
Author: Peter Kerpedjiev
Author-email: pkerpedjiev@gmail.com
License: UNKNOWN
Platform: UNKNOWN
